napari_orientation/__init__.py
napari_orientation/_version.py
napari_orientation/napari.yaml
napari_orientation/orientation_field_widget.py
napari_orientation/_tests/__init__.py
napari_orientation/_tests/test_widget.py
napari_orientation-0.1.5.dist-info/licenses/LICENSE
napari_orientation-0.1.5.dist-info/METADATA
napari_orientation-0.1.5.dist-info/WHEEL
napari_orientation-0.1.5.dist-info/entry_points.txt
napari_orientation-0.1.5.dist-info/top_level.txt
napari_orientation-0.1.5.dist-info/RECORD
